{
    "niv": {
        "branch": "master",
        "description": "Easy dependency management for Nix projects",
        "homepage": "https://github.com/nmattia/niv",
        "owner": "nmattia",
        "repo": "niv",
        "rev": "29ddaaf4e099c3ac0647f5b652469dfc79cd3b53",
        "sha256": "1va6myp07gkspgxfch8z3rs9nyvys6jmgzkys6a2c4j09qxp1bs0",
        "type": "tarball",
        "url": "https://github.com/nmattia/niv/archive/29ddaaf4e099c3ac0647f5b652469dfc79cd3b53.tar.gz",
        "url_template": "https://github.com/<owner>/<repo>/archive/<rev>.tar.gz"
    },
    "nixpkgs": {
        "branch": "release-20.03",
        "description": "Nix Packages collection",
        "homepage": null,
        "owner": "NixOS",
        "repo": "nixpkgs",
        "rev": "760c6ec78cd6d8d658266ac28434a3b04a9e4cbb",
        "sha256": "0aj3cxw9rmbf4msyrwarn1r7idk91vzyf2rcbbjdsjgbx40gfjbv",
        "type": "tarball",
        "url": "https://github.com/NixOS/nixpkgs/archive/760c6ec78cd6d8d658266ac28434a3b04a9e4cbb.tar.gz",
        "url_template": "https://github.com/<owner>/<repo>/archive/<rev>.tar.gz"
    }
}
